yasiu_native/__init__.py
yasiu_native/decorators.py
yasiu_native/time.py
yasiu_native-0.2.4.dist-info/LICENSE
yasiu_native-0.2.4.dist-info/METADATA
yasiu_native-0.2.4.dist-info/WHEEL
yasiu_native-0.2.4.dist-info/top_level.txt
yasiu_native-0.2.4.dist-info/RECORD
